c2c/template/__init__.py
c2c/template/config.py
c2c/template/py.typed
c2c_template-2.4.2.dist-info/LICENSE
c2c_template-2.4.2.dist-info/METADATA
c2c_template-2.4.2.dist-info/WHEEL
c2c_template-2.4.2.dist-info/entry_points.txt
c2c_template-2.4.2.dist-info/RECORD
