Metadata-Version: 2.1
Name: c2c.template
Version: 2.4.2
Summary: Vars collector and template runner.
Home-page: https://github.com/camptocamp/c2c.template
License: BSD-2-Clause
Keywords: template
Author: Camptocamp
Author-email: info@camptocamp.com
Requires-Python: >=3.9
Classifier: Environment :: Console
Classifier: Framework :: Bottle
Classifier: Intended Audience :: Developers
Classifier: License :: OSI Approved :: BSD License
Classifier: Operating System :: OS Independent
Classifier: Programming Language :: Python
Classifier: Programming Language :: Python :: 3
Classifier: Programming Language :: Python :: 3.9
Classifier: Programming Language :: Python :: 3.10
Classifier: Programming Language :: Python :: 3.11
Classifier: Programming Language :: Python :: 3.12
Classifier: Topic :: Utilities
Classifier: Typing :: Typed
Requires-Dist: Jinja2
Requires-Dist: Mako
Requires-Dist: PyYAML
Requires-Dist: bottle
Requires-Dist: pyyaml-include (>=2.0)
Project-URL: Repository, https://github.com/camptocamp/c2c.template
